fastmrt/__init__.py
fastmrt-0.1.0.dist-info/METADATA
fastmrt-0.1.0.dist-info/WHEEL
fastmrt-0.1.0.dist-info/top_level.txt
fastmrt-0.1.0.dist-info/RECORD
